{"total":2,"pageSize":13,"pageCount":1,"data":[{"title":"","uid":"f73a8e23e6f6f669cf99c7dba8fa0722","slug":"算法基础","date":"2023-04-01T04:05:41.693Z","updated":"2023-04-01T04:18:38.864Z","comments":true,"path":"api/articles/算法基础.json","cover":null,"text":"算法基础1.数据结构1.1线性表 数组（int[]、ArrayList） LinkedList ArrayDeque PriorityQueue Set（HashSet、LinkedHashSet、TreeSet） Map（HashMap、LinkedHashMap、TreeMa...","link":"","photos":[],"count_time":{"symbolsCount":263,"symbolsTime":"1 mins."},"categories":[],"tags":[],"author":{"name":"Dajunnnnnn","slug":"blog-author","avatar":"https://img-blog.csdnimg.cn/20210313122054101.png","link":"/","description":"","socials":{"github":"","twitter":"","stackoverflow":"","wechat":"","qq":"","weibo":"","zhihu":"","csdn":"","juejin":"","customs":{}}}},{"title":"Hello World","uid":"b9663f58f18133b35bfe243f3e916a80","slug":"hello-world","date":"2023-03-31T03:02:05.385Z","updated":"2023-03-31T03:02:05.385Z","comments":true,"path":"api/articles/hello-world.json","cover":null,"text":"Welcome to Hexo! This is your very first post. Check documentation for more info. If you get any problems when using Hexo, you can find the ...","link":"","photos":[],"count_time":{"symbolsCount":440,"symbolsTime":"1 mins."},"categories":[],"tags":[],"author":{"name":"Dajunnnnnn","slug":"blog-author","avatar":"https://img-blog.csdnimg.cn/20210313122054101.png","link":"/","description":"","socials":{"github":"","twitter":"","stackoverflow":"","wechat":"","qq":"","weibo":"","zhihu":"","csdn":"","juejin":"","customs":{}}}}]}